odoo/addons/mail_debrand/README.rst
odoo/addons/mail_debrand/__init__.py
odoo/addons/mail_debrand/__manifest__.py
odoo/addons/mail_debrand/i18n/fr.po
odoo/addons/mail_debrand/i18n/mail_debrand.pot
odoo/addons/mail_debrand/i18n/nl.po
odoo/addons/mail_debrand/i18n/pt.po
odoo/addons/mail_debrand/i18n/sl.po
odoo/addons/mail_debrand/i18n/sr_Latn.po
odoo/addons/mail_debrand/models/__init__.py
odoo/addons/mail_debrand/models/mail_template.py
odoo/addons/mail_debrand/models/mail_thread.py
odoo/addons/mail_debrand/readme/CONTRIBUTORS.rst
odoo/addons/mail_debrand/readme/DESCRIPTION.rst
odoo/addons/mail_debrand/readme/HISTORY.rst
odoo/addons/mail_debrand/readme/USAGE.rst
odoo/addons/mail_debrand/static/description/icon.png
odoo/addons/mail_debrand/static/description/icon.svg
odoo/addons/mail_debrand/static/description/index.html
odoo/addons/mail_debrand/tests/__init__.py
odoo/addons/mail_debrand/tests/test_mail_debrand.py
odoo13_addon_mail_debrand-13.0.2.0.1.dist-info/METADATA
odoo13_addon_mail_debrand-13.0.2.0.1.dist-info/WHEEL
odoo13_addon_mail_debrand-13.0.2.0.1.dist-info/top_level.txt
odoo13_addon_mail_debrand-13.0.2.0.1.dist-info/RECORD
